ipywidgets_game_jugs/Jugs.py
ipywidgets_game_jugs/JugsPlayer.py
ipywidgets_game_jugs/SingleJug.py
ipywidgets_game_jugs/__init__.py
ipywidgets_game_jugs/__global__/__init__.py
ipywidgets_game_jugs/__global__/en.py
ipywidgets_game_jugs/__global__/fr.py
ipywidgets_game_jugs-0.2.0.dist-info/LICENSE.txt
ipywidgets_game_jugs-0.2.0.dist-info/METADATA
ipywidgets_game_jugs-0.2.0.dist-info/WHEEL
ipywidgets_game_jugs-0.2.0.dist-info/top_level.txt
ipywidgets_game_jugs-0.2.0.dist-info/RECORD
