Metadata-Version: 2.1
Name: ipywidgets-game-jugs
Version: 0.2.0
Summary: The water jug riddle with Jupyter Notebook
Home-page: https://gitlab.u-psud.fr/edwige.gros/ipywidgets-games.git
Author: Edwige GROS
Author-email: edwige.gros@laposte.net
License: UNKNOWN
Platform: UNKNOWN
Classifier: Programming Language :: Python :: 3
Classifier: License :: OSI Approved :: MIT License
Classifier: Operating System :: OS Independent
Requires-Python: >=3.6
Requires-Dist: timer
Requires-Dist: ipywidgets
Requires-Dist: ipycanvas
Requires-Dist: valueplayerwidget
